<?xml version="1.0" encoding="utf-8"?>
<DicResult><head/><def pos="noun" ts="ˈɑːkeɪnʤəl"><text>Archangel</text><tr pos="существительное"><text>Архангел</text><ex><text>Archangel Gabriel</text><tr><text>Архангел Гавриил</text></tr></ex></tr><tr pos="существительное"><text>архистратиг</text><ex><text>Archangel Michael</text><tr><text>архистратиг Михаил</text></tr></ex></tr></def><def pos="adjective" ts="ˈɑːkeɪnʤəl"><text>Archangel</text><tr pos="прилагательное"><text>Архангельский</text><ex><text>Archangel cathedral</text><tr><text>Архангельский собор</text></tr></ex></tr></def></DicResult>