<?xml version="1.0" encoding="utf-8"?>
<DicResult><head/><def pos="adjective" ts="əˈrɪθmətɪk"><text>arithmetic</text><tr pos="прилагательное"><text>арифметический</text><mean><text>arithmetical</text></mean><ex><text>arithmetic progression</text><tr><text>арифметическая прогрессия</text></tr></ex></tr></def><def pos="noun" ts="əˈrɪθmətɪk"><text>arithmetic</text><tr pos="существительное"><text>арифметика</text><mean><text>math</text></mean><ex><text>integer arithmetic</text><tr><text>целочисленная арифметика</text></tr></ex></tr></def></DicResult>