<?xml version="1.0" encoding="utf-8"?>
<DicResult><head/><def pos="noun" ts="ɑːm"><text>arm</text><tr pos="существительное"><text>рука</text><syn pos="существительное"><text>оружие</text></syn><syn pos="существительное"><text>плечо</text></syn><syn pos="существительное"><text>рукав</text></syn><syn pos="существительное"><text>локоть</text></syn><syn pos="существительное"><text>предплечье</text></syn><mean><text>hand</text></mean><mean><text>weapon</text></mean><mean><text>shoulder</text></mean><mean><text>sleeve</text></mean><mean><text>elbow</text></mean><mean><text>forearm</text></mean><ex><text>outstretched arm</text><tr><text>протянув руку</text></tr></ex><ex><text>small-arms</text><tr><text>стрелковое оружие</text></tr></ex><ex><text>left arm</text><tr><text>левое плечо</text></tr></ex><ex><text>sweeping arm</text><tr><text>сметающий рукав</text></tr></ex><ex><text>my arm</text><tr><text>мои локти</text></tr></ex><ex><text>right arm</text><tr><text>правое предплечье</text></tr></ex></tr><tr pos="существительное"><text>рукоятка</text><syn pos="существительное"><text>рычаг</text></syn><syn pos="существительное"><text>кронштейн</text></syn><syn pos="существительное"><text>подлокотник</text></syn><mean><text>handle</text></mean><mean><text>lever</text></mean><mean><text>armrest</text></mean><ex><text>your arm</text><tr><text>ваша рукоятка</text></tr></ex><ex><text>swivel arm</text><tr><text>поворотный рычаг</text></tr></ex><ex><text>pendant arm</text><tr><text>подвесной кронштейн</text></tr></ex><ex><text>on the arm</text><tr><text>на подлокотник</text></tr></ex></tr><tr pos="существительное"><text>мышца</text><mean><text>muscle</text></mean><ex><text>arm muscles</text><tr><text>мышцы рук</text></tr></ex></tr></def><def pos="verb" ts="ɑːm"><text>arm</text><tr pos="глагол"><text>вооружиться</text><syn pos="глагол"><text>вооружать</text></syn><syn pos="глагол"><text>вооружить</text></syn><mean><text>arm yourself</text></mean><ex><text>arm Georgia</text><tr><text>вооружать Грузию</text></tr></ex><ex><text>in armed conflict</text><tr><text>в вооруженном конфликте</text></tr></ex></tr></def></DicResult>