<?xml version="1.0" encoding="utf-8"?>
<DicResult><head/><def pos="noun" ts="beɪl"><text>bail</text><tr pos="существительное"><text>залог</text><syn pos="существительное"><text>поручитель</text></syn><mean><text>pledge</text></mean><mean><text>guarantor</text></mean><ex><text>release on bail</text><tr><text>освобождение под залог</text></tr></ex></tr><tr pos="существительное"><text>порука</text><syn pos="существительное"><text>поручительство</text></syn><mean><text>surety</text></mean><ex><text>circular bail</text><tr><text>круговая порука</text></tr></ex><ex><text>on bail</text><tr><text>под поручительство</text></tr></ex></tr><tr pos="существительное"><text>спасение</text><mean><text>rescue</text></mean></tr><tr pos="существительное"><text>внесение залога</text></tr></def><def pos="verb" ts="beɪl"><text>bail</text><tr pos="глагол"><text>выручить</text><syn pos="глагол"><text>спасать</text></syn><syn pos="глагол"><text>выручать</text></syn><mean><text>rescue</text></mean><mean><text>save</text></mean></tr><tr pos="глагол"><text>спасти</text><mean><text>save</text></mean></tr><tr pos="глагол"><text>внести залог</text></tr><tr pos="глагол"><text>выкупить</text></tr><tr pos="глагол"><text>вытаскивать</text></tr><tr pos="глагол"><text>поручиться</text></tr></def></DicResult>