<?xml version="1.0" encoding="utf-8"?>
<DicResult><head/><def pos="noun" ts="ˈbɑːbərɪzm"><text>barbarism</text><tr pos="существительное"><text>варварство</text><syn pos="существительное"><text>дикость</text></syn><mean><text>barbarity</text></mean><mean><text>savagery</text></mean><ex><text>capitalist barbarism</text><tr><text>капиталистическое варварство</text></tr></ex></tr></def><def pos="adjective" ts="ˈbɑːbərɪzm"><text>barbarism</text><tr pos="прилагательное"><text>варварский</text><mean><text>barbarian</text></mean></tr></def></DicResult>