<?xml version="1.0" encoding="utf-8"?>
<DicResult><head/><def pos="noun" ts="beɪsn"><text>basin</text><tr pos="существительное"><text>бассейн</text><syn pos="существительное"><text>водосбор</text></syn><mean><text>pool</text></mean><mean><text>catchment</text></mean><ex><text>catchment basin</text><tr><text>водосборный бассейн</text></tr></ex></tr><tr pos="существительное"><text>умывальник</text><syn pos="существительное"><text>таз</text></syn><syn pos="существительное"><text>раковина</text></syn><syn pos="существительное"><text>умывальница</text></syn><mean><text>washbasin</text></mean><mean><text>pelvis</text></mean><mean><text>sink</text></mean><mean><text>laver</text></mean><ex><text>copper basin</text><tr><text>медный таз</text></tr></ex><ex><text>in the basin</text><tr><text>в раковине</text></tr></ex></tr><tr pos="существительное"><text>тазик</text><syn pos="существительное"><text>миска</text></syn><mean><text>bowl</text></mean><ex><text>wash basin</text><tr><text>тазик мытья</text></tr></ex><ex><text>into the basin</text><tr><text>в миску</text></tr></ex></tr><tr pos="существительное"><text>водоем</text><mean><text>reservoir</text></mean></tr><tr pos="существительное"><text>котловина</text><mean><text>hollow</text></mean><ex><text>lake basins</text><tr><text>озерные котловины</text></tr></ex></tr></def><def pos="adjective" ts="beɪsn"><text>basin</text><tr pos="прилагательное"><text>бассейновый</text><mean><text>pool</text></mean><ex><text>Dnipro basin Council</text><tr><text>Днепровский бассейновый Совет</text></tr></ex></tr></def></DicResult>