<?xml version="1.0" encoding="utf-8"?>
<DicResult><head/><def pos="noun" ts="baɪˈəʊ"><text>bio</text><tr pos="существительное"><text>био</text><ex><text>bio-fuels</text><tr><text>био топлива</text></tr></ex></tr><tr pos="существительное"><text>биотопливо</text><syn pos="существительное"><text>биоэнергетика</text></syn><syn pos="существительное"><text>биомасса</text></syn><mean><text>biofuel</text></mean><mean><text>bioenergy</text></mean><mean><text>biomass</text></mean></tr><tr pos="существительное"><text>биография</text><mean><text>biography</text></mean><ex><text>short bio</text><tr><text>краткая биография</text></tr></ex></tr><tr pos="существительное"><text>биотехнология</text><mean><text>biotechnology</text></mean></tr><tr pos="существительное"><text>биополе</text></tr><tr pos="существительное"><text>ОБП</text></tr></def><def pos="adjective" ts="baɪˈəʊ"><text>bio</text><tr pos="прилагательное"><text>биологический</text><syn pos="прилагательное"><text>биоэнергетический</text></syn><mean><text>bioenergy</text></mean><ex><text>bio-weapon</text><tr><text>биологическое оружие</text></tr></ex></tr></def></DicResult>