<?xml version="1.0" encoding="utf-8"?>
<DicResult><head/><def pos="noun" ts="ˈbriːdə"><text>breeder</text><tr pos="существительное"><text>заводчик</text><syn pos="существительное"><text>заводчица</text></syn><mean><text>owner</text></mean><ex><text>dog breeder</text><tr><text>заводчик собак</text></tr></ex></tr><tr pos="существительное"><text>селекционер</text><ex><text>plant breeders</text><tr><text>селекционеры растений</text></tr></ex></tr><tr pos="существительное"><text>животновод</text><syn pos="существительное"><text>скотовод</text></syn><mean><text>cattleman</text></mean></tr><tr pos="существительное"><text>производитель</text><mean><text>manufacturer</text></mean></tr><tr pos="существительное"><text>размножитель</text><ex><text>breeder reactor</text><tr><text>реактор-размножитель</text></tr></ex></tr><tr pos="существительное"><text>свиновод</text></tr><tr pos="существительное"><text>производительница</text><mean><text>female breeder</text></mean></tr></def><def pos="adjective" ts="ˈbriːdə"><text>breeder</text><tr pos="прилагательное"><text>племенной</text><mean><text>breeding</text></mean></tr></def></DicResult>