<?xml version="1.0" encoding="utf-8"?>
<DicResult><head/><def pos="adverb" ts="ˈbrɪlɪəntlɪ"><text>brilliantly</text><tr pos="наречие"><text>блестяще</text><syn pos="наречие"><text>блистательно</text></syn><mean><text>splendidly</text></mean><ex><text>brilliantly play</text><tr><text>блестяще сыграть</text></tr></ex></tr><tr pos="наречие"><text>великолепно</text><syn pos="наречие"><text>прекрасно</text></syn><syn pos="наречие"><text>превосходно</text></syn><syn pos="наречие"><text>замечательно</text></syn><mean><text>superbly</text></mean><mean><text>perfectly</text></mean><mean><text>excellently</text></mean><mean><text>wonderfully</text></mean></tr><tr pos="наречие"><text>гениально</text></tr><tr pos="наречие"><text>виртуозно</text><syn pos="наречие"><text>мастерски</text></syn></tr><tr pos="наречие"><text>ослепительно</text><mean><text>bright</text></mean></tr></def><def pos="adjective" ts="ˈbrɪlɪəntlɪ"><text>brilliantly</text><tr pos="прилагательное"><text>блестящий</text><mean><text>bright</text></mean></tr></def><def pos="noun" ts="ˈbrɪlɪəntlɪ"><text>brilliantly</text><tr pos="существительное"><text>с блеском</text><mean><text>with shine</text></mean></tr><tr pos="существительное"><text>гениальн</text></tr></def></DicResult>