<?xml version="1.0" encoding="utf-8"?>
<DicResult><head/><def pos="noun" ts="ˈbrʌðəhʊd"><text>brotherhood</text><tr pos="существительное"><text>братство</text><syn pos="существительное"><text>братия</text></syn><mean><text>fraternity</text></mean><ex><text>Sufi brotherhood</text><tr><text>суфийское братство</text></tr></ex><ex><text>journalistic brotherhood</text><tr><text>журналистская братия</text></tr></ex></tr><tr pos="существительное"><text>братские отношения</text><mean><text>fraternal relations</text></mean></tr></def><def pos="adjective" ts="ˈbrʌðəhʊd"><text>brotherhood</text><tr pos="прилагательное"><text>братский</text><mean><text>sister</text></mean><ex><text>brotherhood school</text><tr><text>братская школа</text></tr></ex></tr></def></DicResult>