<?xml version="1.0" encoding="utf-8"?>
<DicResult><head/><def pos="noun" ts="ˈbraʊzər"><text>browser</text><tr pos="существительное"><text>браузер</text><syn pos="существительное"><text>обозреватель</text></syn><syn pos="существительное"><text>навигатор</text></syn><mean><text>navigator</text></mean><ex><text>Maxthon browser</text><tr><text>браузер Maxthon</text></tr></ex><ex><text>Internet Explorer browser</text><tr><text>обозреватель Internet Explorer</text></tr></ex><ex><text>web browser</text><tr><text>веб-навигатор</text></tr></ex></tr><tr pos="существительное"><text>просмотрщик</text><syn pos="существительное"><text>программа просмотра</text></syn><mean><text>viewer</text></mean></tr></def><def pos="verb" ts="ˈbraʊzər"><text>browser</text><tr pos="глагол"><text>объедать</text></tr></def></DicResult>