<?xml version="1.0" encoding="utf-8"?>
<DicResult><head/><def pos="noun" ts="ˈbʌnɪ"><text>bunny</text><tr pos="существительное"><text>Банни</text></tr><tr pos="существительное"><text>зайчик</text><syn pos="существительное"><text>заяц</text></syn><syn pos="существительное"><text>зайка</text></syn><mean><text>hare</text></mean><ex><text>Easter bunnies</text><tr><text>пасхальные зайчики</text></tr></ex></tr><tr pos="существительное"><text>кролик</text><mean><text>rabbit</text></mean><ex><text>Easter bunny</text><tr><text>пасхальный кролик</text></tr></ex></tr></def></DicResult>