<?xml version="1.0" encoding="utf-8"?>
<DicResult><head/><def pos="noun" ts="ˈkænəpɪ"><text>canopy</text><tr pos="существительное"><text>навес</text><syn pos="существительное"><text>купол</text></syn><syn pos="существительное"><text>козырек</text></syn><syn pos="существительное"><text>тент</text></syn><syn pos="существительное"><text>парашют</text></syn><syn pos="существительное"><text>шатер</text></syn><mean><text>awning</text></mean><mean><text>dome</text></mean><mean><text>overhang</text></mean><mean><text>parachute</text></mean><mean><text>tent</text></mean><ex><text>under a canopy</text><tr><text>под навесом</text></tr></ex><ex><text>your canopy</text><tr><text>ваш купол</text></tr></ex></tr><tr pos="существительное"><text>балдахин</text><syn pos="существительное"><text>полог</text></syn><mean><text>curtain</text></mean><ex><text>canopied bed</text><tr><text>кровать с балдахином</text></tr></ex><ex><text>under the canopy</text><tr><text>под пологом</text></tr></ex></tr><tr pos="существительное"><text>сень</text><ex><text>hothouse canopy</text><tr><text>теплицевая сень</text></tr></ex></tr><tr pos="существительное"><text>покров</text><mean><text>cover</text></mean></tr><tr pos="существительное"><text>фонарь</text></tr><tr pos="существительное"><text>фонарь кабины</text></tr></def></DicResult>