<?xml version="1.0" encoding="utf-8"?>
<DicResult><head/><def pos="noun" ts="kənˈtendə"><text>contender</text><tr pos="существительное"><text>соперник</text><syn pos="существительное"><text>конкурент</text></syn><mean><text>rival</text></mean><mean><text>competitor</text></mean><ex><text>presidential contender</text><tr><text>президентский соперник</text></tr></ex><ex><text>serious contender</text><tr><text>серьезный конкурент</text></tr></ex></tr><tr pos="существительное"><text>претендент</text><mean><text>applicant</text></mean><ex><text>among the contenders</text><tr><text>среди претендентов</text></tr></ex></tr></def></DicResult>