<?xml version="1.0" encoding="utf-8"?>
<DicResult><head/><def pos="noun" ts="kənˈteɪnmənt"><text>containment</text><tr pos="существительное"><text>сдерживание</text><syn pos="существительное"><text>удержание</text></syn><mean><text>deterrence</text></mean><mean><text>retention</text></mean><ex><text>nuclear containment</text><tr><text>ядерное сдерживание</text></tr></ex><ex><text>containment systems</text><tr><text>система удержания</text></tr></ex></tr><tr pos="существительное"><text>оболочка</text><mean><text>shell</text></mean><ex><text>secondary containment</text><tr><text>вторичная защитная оболочка</text></tr></ex></tr><tr pos="существительное"><text>защитная оболочка</text><mean><text>protective shell</text></mean></tr><tr pos="существительное"><text>локализация</text><mean><text>confinement</text></mean></tr><tr pos="существительное"><text>герметичность</text><syn pos="существительное"><text>герметизация</text></syn><syn pos="существительное"><text>разгерметизация</text></syn><mean><text>tightness</text></mean><mean><text>seal</text></mean></tr><tr pos="существительное"><text>вложенность</text><mean><text>enclosure</text></mean></tr></def></DicResult>