<?xml version="1.0" encoding="utf-8"?>
<DicResult><head/><def pos="adjective" ts="ˈkɔnˈveks"><text>convex</text><tr pos="прилагательное"><text>выпуклый</text><mean><text>arched</text></mean><ex><text>convex polytope</text><tr><text>выпуклый многогранник</text></tr></ex></tr></def><def pos="noun" ts="ˈkɔnˈveks"><text>convex</text><tr pos="существительное"><text>выпуклость</text></tr></def><def pos="adverb" ts="ˈkɔnˈveks"><text>convex</text><tr pos="наречие"><text>выпукло</text></tr></def></DicResult>