<?xml version="1.0" encoding="utf-8"?>
<DicResult><head/><def pos="verb" ts="kənˈvɪns"><text>convince</text><tr pos="глагол"><text>убедить</text><syn pos="глагол"><text>убеждать</text></syn><syn pos="глагол"><text>уговорить</text></syn><syn pos="глагол"><text>переубедить</text></syn><syn pos="глагол"><text>переубеждать</text></syn><mean><text>persuade</text></mean><ex><text>finally convince</text><tr><text>окончательно убедить</text></tr></ex><ex><text>convince me</text><tr><text>убеждать меня</text></tr></ex></tr><tr pos="глагол"><text>убедиться</text><syn pos="глагол"><text>уверить</text></syn><mean><text>verify</text></mean><mean><text>assure</text></mean></tr><tr pos="глагол"><text>доказать</text><mean><text>prove</text></mean></tr><tr pos="глагол"><text>внушить</text><mean><text>impress</text></mean></tr></def><def pos="noun" ts="kənˈvɪns"><text>convince</text><tr pos="существительное"><text>убеждение</text></tr></def></DicResult>