<?xml version="1.0" encoding="utf-8"?>
<DicResult><head/><def pos="verb" ts="diːˈseləreɪt"><text>decelerate</text><tr pos="глагол"><text>замедлиться</text><syn pos="глагол"><text>замедляться</text></syn><syn pos="глагол"><text>замедлять</text></syn><syn pos="глагол"><text>тормозить</text></syn><syn pos="глагол"><text>замедлить</text></syn><mean><text>slow</text></mean><mean><text>inhibit</text></mean><ex><text>decelerating potential</text><tr><text>тормозящий потенциал</text></tr></ex></tr><tr pos="глагол"><text>сбросить скорость</text><mean><text>slow down</text></mean></tr></def><def pos="noun" ts="diːˈseləreɪt"><text>decelerate</text><tr pos="существительное"><text>замедление</text><mean><text>slow</text></mean></tr></def></DicResult>