<?xml version="1.0" encoding="utf-8"?>
<DicResult><head/><def pos="adverb" ts="dɪˈfensɪvlɪ"><text>defensively</text><tr pos="наречие"><text>оборонительно</text></tr><tr pos="наречие"><text>защитительно</text></tr></def><def pos="adjective" ts="dɪˈfensɪvlɪ"><text>defensively</text><tr pos="прилагательное"><text>оборонительный</text></tr></def><def pos="verb" ts="dɪˈfensɪvlɪ"><text>defensively</text><tr pos="глагол"><text>защищаться</text><mean><text>defend ourselves</text></mean></tr></def></DicResult>