<?xml version="1.0" encoding="utf-8"?>
<DicResult><head/><def pos="noun" ts="dɪˈtekʃn"><text>detection</text><tr pos="существительное"><text>обнаружение</text><syn pos="существительное"><text>выявление</text></syn><syn pos="существительное"><text>определение</text></syn><syn pos="существительное"><text>детектирование</text></syn><syn pos="существительное"><text>распознавание</text></syn><mean><text>discovery</text></mean><mean><text>identification</text></mean><mean><text>definition</text></mean><mean><text>detecting</text></mean><mean><text>recognition</text></mean><ex><text>heuristic detection</text><tr><text>эвристическое обнаружение</text></tr></ex><ex><text>timely detection</text><tr><text>своевременное выявление</text></tr></ex><ex><text>quantitative detection</text><tr><text>количественное определение</text></tr></ex><ex><text>loop detection</text><tr><text>детектирование петель</text></tr></ex><ex><text>automatic detection</text><tr><text>автоматическое распознавание</text></tr></ex></tr><tr pos="существительное"><text>раскрываемость</text><mean><text>detection rate</text></mean><ex><text>crime detection</text><tr><text>раскрываемость преступлений</text></tr></ex></tr></def></DicResult>