<?xml version="1.0" encoding="utf-8"?>
<DicResult><head/><def pos="noun" ts="dɪˈvɪnɪtɪ"><text>divinity</text><tr pos="существительное"><text>божественность</text><syn pos="существительное"><text>божество</text></syn><mean><text>deity</text></mean><ex><text>Christ&apos;s divinity</text><tr><text>божественность Христа</text></tr></ex><ex><text>his divinity</text><tr><text>его божество</text></tr></ex></tr><tr pos="существительное"><text>богословие</text><mean><text>theology</text></mean><ex><text>doctor of divinity</text><tr><text>доктор богословия</text></tr></ex></tr><tr pos="существительное"><text>божественная природа</text></tr></def><def pos="adjective" ts="dɪˈvɪnɪtɪ"><text>divinity</text><tr pos="прилагательное"><text>божественный</text><mean><text>divine</text></mean><ex><text>with divinity</text><tr><text>с божественным</text></tr></ex></tr></def></DicResult>