<?xml version="1.0" encoding="utf-8"?>
<DicResult><head/><def pos="adjective" ts="dɪˈvɪʒənl"><text>divisional</text><tr pos="прилагательное"><text>участковый</text><ex><text>divisional lesnichestvo</text><tr><text>участковое лесничество</text></tr></ex></tr><tr pos="прилагательное"><text>дивизионный</text></tr><tr pos="прилагательное"><text>разделительный</text></tr></def><def pos="noun" ts="dɪˈvɪʒənl"><text>divisional</text><tr pos="существительное"><text>подразделение</text><ex><text>divisional sales</text><tr><text>продажи подразделения</text></tr></ex></tr></def></DicResult>