<?xml version="1.0" encoding="utf-8"?>
<DicResult><head/><def pos="adverb" ts="iːkəˈnɔmɪkəlɪ"><text>economically</text><tr pos="наречие"><text>экономически</text><mean><text>financially</text></mean><ex><text>economically feasible</text><tr><text>экономически обоснованный</text></tr></ex></tr><tr pos="наречие"><text>экономично</text><syn pos="наречие"><text>экономно</text></syn><mean><text>cost-effectively</text></mean></tr><tr pos="наречие"><text>хозяйственно</text></tr></def><def pos="adjective" ts="iːkəˈnɔmɪkəlɪ"><text>economically</text><tr pos="прилагательное"><text>экономический</text><ex><text>economically viable</text><tr><text>экономическая жизнеспособность</text></tr></ex></tr></def><def pos="noun" ts="iːkəˈnɔmɪkəlɪ"><text>economically</text><tr pos="существительное"><text>в экономическом отношении</text><syn pos="существительное"><text>в экономическом плане</text></syn><mean><text>in economic terms</text></mean></tr><tr pos="существительное"><text>с экономической точки</text><mean><text>from economic point</text></mean></tr><tr pos="существительное"><text>с экономической</text><mean><text>from an economic</text></mean></tr><tr pos="существительное"><text>в экономическом</text></tr></def></DicResult>