<?xml version="1.0" encoding="utf-8"?>
<DicResult><head/><def pos="noun" ts="ˈfɛənɪs"><text>fairness</text><tr pos="существительное"><text>справедливость</text><mean><text>justice</text></mean><ex><text>procedural fairness</text><tr><text>процессуальная справедливость</text></tr></ex></tr><tr pos="существительное"><text>честность</text><syn pos="существительное"><text>добросовестность</text></syn><mean><text>honesty</text></mean><mean><text>integrity</text></mean></tr><tr pos="существительное"><text>беспристрастность</text><syn pos="существительное"><text>объективность</text></syn><syn pos="существительное"><text>непредвзятость</text></syn><mean><text>impartiality</text></mean><mean><text>objectivity</text></mean></tr><tr pos="существительное"><text>равнодоступность</text><mean><text>equal access</text></mean></tr><tr pos="существительное"><text>справедливое отношение</text><mean><text>fair treatment</text></mean></tr><tr pos="существительное"><text>показательность</text></tr></def><def pos="adjective" ts="ˈfɛənɪs"><text>fairness</text><tr pos="прилагательное"><text>справедливый</text><mean><text>fair</text></mean></tr></def></DicResult>