<?xml version="1.0" encoding="utf-8"?>
<DicResult><head/><def pos="adjective" ts="ʤɪˈlætɪnəs"><text>gelatinous</text><tr pos="прилагательное"><text>желатиновый</text><ex><text>gelatinous capsules</text><tr><text>желатиновые капсулы</text></tr></ex></tr><tr pos="прилагательное"><text>желеобразный</text><syn pos="прилагательное"><text>студенистый</text></syn><ex><text>gelatinous mass</text><tr><text>желеобразная масса</text></tr></ex></tr><tr pos="прилагательное"><text>желетелый</text></tr><tr pos="прилагательное"><text>гелеобразный</text><mean><text>gel-like</text></mean></tr></def></DicResult>