<?xml version="1.0" encoding="utf-8"?>
<DicResult><head/><def pos="noun" ts="glɪʧ"><text>glitch</text><tr pos="существительное"><text>сбой</text><mean><text>failure</text></mean><ex><text>technical glitch</text><tr><text>технический сбой</text></tr></ex></tr><tr pos="существительное"><text>глюк</text><mean><text>bug</text></mean></tr><tr pos="существительное"><text>затруднение</text><mean><text>difficulty</text></mean></tr><tr pos="существительное"><text>небольшое затруднение</text></tr></def></DicResult>