<?xml version="1.0" encoding="utf-8"?>
<DicResult><head/><def pos="noun" ts="gɪlt"><text>guilt</text><tr pos="существительное"><text>виновность</text><syn pos="существительное"><text>вина</text></syn><mean><text>culpability</text></mean><mean><text>fault</text></mean><ex><text>presumption of guilt</text><tr><text>презумпция виновности</text></tr></ex><ex><text>their guilt</text><tr><text>их вина</text></tr></ex></tr><tr pos="существительное"><text>вся вина</text><mean><text>all the blame</text></mean></tr><tr pos="существительное"><text>угрызения</text><mean><text>remorse</text></mean></tr><tr pos="существительное"><text>ощущение вины</text></tr></def><def pos="adjective" ts="gɪlt"><text>guilt</text><tr pos="прилагательное"><text>виновный</text><syn pos="прилагательное"><text>виноватый</text></syn><mean><text>culprit</text></mean><mean><text>blame</text></mean></tr></def></DicResult>