<?xml version="1.0" encoding="utf-8"?>
<DicResult><head/><def pos="noun" ts="ˈɪmɪʤərɪ"><text>imagery</text><tr pos="существительное"><text>изображение</text><syn pos="существительное"><text>образ</text></syn><syn pos="существительное"><text>скульптура</text></syn><mean><text>image</text></mean><ex><text>photographic imagery</text><tr><text>фотографические изображения</text></tr></ex><ex><text>visual imagery</text><tr><text>визуальный образ</text></tr></ex></tr><tr pos="существительное"><text>снимки</text><ex><text>satellite imagery</text><tr><text>спутниковые снимки</text></tr></ex></tr><tr pos="существительное"><text>съемка</text><mean><text>shooting</text></mean><ex><text>radar imagery</text><tr><text>радиолокационная съемка</text></tr></ex></tr><tr pos="существительное"><text>образность</text><ex><text>science of imagery</text><tr><text>наука образности</text></tr></ex></tr><tr pos="существительное"><text>воображение</text><mean><text>imagination</text></mean><ex><text>guided imagery</text><tr><text>управляемое воображение</text></tr></ex></tr></def><def pos="adjective" ts="ˈɪmɪʤərɪ"><text>imagery</text><tr pos="прилагательное"><text>образный</text></tr></def></DicResult>