<?xml version="1.0" encoding="utf-8"?>
<DicResult><head/><def pos="noun" ts="ˈɪmɪgrənt"><text>immigrant</text><tr pos="существительное"><text>иммигрант</text><syn pos="существительное"><text>эмигрант</text></syn><syn pos="существительное"><text>мигрант</text></syn><syn pos="существительное"><text>переселенец</text></syn><syn pos="существительное"><text>выходец</text></syn><syn pos="существительное"><text>эмигрантка</text></syn><mean><text>emigrant</text></mean><mean><text>migrant</text></mean><ex><text>undocumented immigrant</text><tr><text>нелегальный иммигрант</text></tr></ex><ex><text>illegal immigrant</text><tr><text>нелегальный эмигрант</text></tr></ex><ex><text>illegal immigrants</text><tr><text>нелегальные мигранты</text></tr></ex><ex><text>compelled immigrant</text><tr><text>вынужденный переселенец</text></tr></ex><ex><text>immigrants from Russia</text><tr><text>выходцы из России</text></tr></ex></tr></def><def pos="adjective" ts="ˈɪmɪgrənt"><text>immigrant</text><tr pos="прилагательное"><text>иммигрантский</text><ex><text>immigrant community</text><tr><text>иммигрантская община</text></tr></ex></tr><tr pos="прилагательное"><text>иммиграционный</text><mean><text>immigration</text></mean><ex><text>immigrant visa</text><tr><text>иммиграционная виза</text></tr></ex></tr></def></DicResult>