<?xml version="1.0" encoding="utf-8"?>
<DicResult><head/><def pos="noun" ts="ɪnˈædɪkwəsɪ"><text>inadequacy</text><tr pos="существительное"><text>неадекватность</text><ex><text>feelings of inadequacy</text><tr><text>чувство неадекватности</text></tr></ex></tr><tr pos="существительное"><text>недостаток</text><syn pos="существительное"><text>недостаточность</text></syn><syn pos="существительное"><text>несовершенство</text></syn><mean><text>disadvantage</text></mean><mean><text>insufficiency</text></mean><mean><text>imperfection</text></mean></tr><tr pos="существительное"><text>несоответствие</text><syn pos="существительное"><text>несостоятельность</text></syn><mean><text>inconsistency</text></mean><ex><text>own inadequacy</text><tr><text>собственная несостоятельность</text></tr></ex></tr><tr pos="существительное"><text>неполноценность</text><mean><text>inferiority</text></mean></tr><tr pos="существительное"><text>непригодность</text></tr><tr pos="существительное"><text>неудовлетворительность</text></tr></def></DicResult>