<?xml version="1.0" encoding="utf-8"?>
<DicResult><head/><def pos="pronoun" ts="ɪtˈself"><text>itself</text><tr pos="местоимение"><text>самое</text><ex><text>into heaven itself</text><tr><text>в самое небо</text></tr></ex></tr><tr pos="местоимение"><text>таковая</text></tr><tr pos="местоимение"><text>собственно сам</text></tr></def><def pos="adjective" ts="ɪtˈself"><text>itself</text><tr pos="прилагательное"><text>самостоятельный</text></tr><tr pos="прилагательное"><text>непосредственный</text></tr></def><def pos="particle" ts="ɪtˈself"><text>itself</text><tr pos="частица"><text>собственно</text></tr></def></DicResult>