<?xml version="1.0" encoding="utf-8"?>
<DicResult><head/><def pos="adverb" ts="ʤʌstɪˈfaɪəblɪ"><text>justifiably</text><tr pos="наречие"><text>справедливо</text><syn pos="наречие"><text>обоснованно</text></syn><syn pos="наречие"><text>оправданно</text></syn><mean><text>rightly</text></mean><mean><text>reasonably</text></mean></tr></def><def pos="adjective" ts="ʤʌstɪˈfaɪəblɪ"><text>justifiably</text><tr pos="прилагательное"><text>справедливый</text><mean><text>justly</text></mean></tr></def><def pos="noun" ts="ʤʌstɪˈfaɪəblɪ"><text>justifiably</text><tr pos="существительное"><text>по праву</text><mean><text>rightfully</text></mean></tr></def></DicResult>