<?xml version="1.0" encoding="utf-8"?>
<DicResult><head/><def pos="noun" ts="ˈmeɪsnrɪ"><text>masonry</text><tr pos="существительное"><text>кладка</text><syn pos="существительное"><text>кирпичная кладка</text></syn><mean><text>brickwork</text></mean><ex><text>brick masonry</text><tr><text>кирпичная кладка</text></tr></ex></tr><tr pos="существительное"><text>каменная кладка</text></tr><tr pos="существительное"><text>масонство</text><ex><text>co-masonry</text><tr><text>со-масонство</text></tr></ex></tr><tr pos="существительное"><text>кирпич</text></tr><tr pos="существительное"><text>каменщик</text></tr></def><def pos="adjective" ts="ˈmeɪsnrɪ"><text>masonry</text><tr pos="прилагательное"><text>каменный</text><syn pos="прилагательное"><text>кирпичный</text></syn><mean><text>stone</text></mean><mean><text>brick</text></mean><ex><text>stone masonry</text><tr><text>каменная кладка</text></tr></ex></tr><tr pos="прилагательное"><text>кладочный</text><ex><text>masonry mortar</text><tr><text>кладочный раствор</text></tr></ex></tr></def></DicResult>