<?xml version="1.0" encoding="utf-8"?>
<DicResult><head/><def pos="adverb" ts="məˈtɪərɪəlɪ"><text>materially</text><tr pos="наречие"><text>существенно</text><syn pos="наречие"><text>материально</text></syn><syn pos="наречие"><text>значительно</text></syn><mean><text>substantially</text></mean><mean><text>significantly</text></mean><ex><text>differ materially</text><tr><text>существенно отличаться</text></tr></ex><ex><text>materially responsible person</text><tr><text>материально ответственное лицо</text></tr></ex></tr></def><def pos="adjective" ts="məˈtɪərɪəlɪ"><text>materially</text><tr pos="прилагательное"><text>материальный</text><syn pos="прилагательное"><text>существенный</text></syn><mean><text>substantially</text></mean></tr></def></DicResult>