<?xml version="1.0" encoding="utf-8"?>
<DicResult><head/><def pos="noun" ts="mɪʃn"><text>mission</text><tr pos="существительное"><text>миссия</text><syn pos="существительное"><text>представительство</text></syn><mean><text>representation</text></mean><ex><text>OSART mission</text><tr><text>миссия OSART</text></tr></ex><ex><text>permanent diplomatic mission</text><tr><text>постоянное дипломатическое представительство</text></tr></ex></tr><tr pos="существительное"><text>полет</text><mean><text>flight</text></mean><ex><text>Mars mission</text><tr><text>полет на Марс</text></tr></ex></tr><tr pos="существительное"><text>задание</text><syn pos="существительное"><text>поручение</text></syn><mean><text>task</text></mean><mean><text>errand</text></mean><ex><text>flight mission</text><tr><text>полетное задание</text></tr></ex><ex><text>special mission</text><tr><text>особое поручение</text></tr></ex></tr><tr pos="существительное"><text>предназначение</text><syn pos="существительное"><text>призвание</text></syn><mean><text>destiny</text></mean><mean><text>vocation</text></mean><ex><text>main mission</text><tr><text>главное предназначение</text></tr></ex><ex><text>our mission</text><tr><text>наше призвание</text></tr></ex></tr><tr pos="существительное"><text>командировка</text><mean><text>trip</text></mean><ex><text>official missions</text><tr><text>служебные командировки</text></tr></ex></tr></def><def pos="adjective" ts="mɪʃn"><text>mission</text><tr pos="прилагательное"><text>миссионерский</text><mean><text>missionary</text></mean><ex><text>mission fields</text><tr><text>миссионерское поприще</text></tr></ex></tr></def></DicResult>