<?xml version="1.0" encoding="utf-8"?>
<DicResult><head/><def pos="noun" ts="ˈmaʊntɪntɒp"><text>mountaintop</text><tr pos="существительное"><text>вершина</text><syn pos="существительное"><text>гора</text></syn><mean><text>peak</text></mean><mean><text>mountain</text></mean><ex><text>on a mountaintop</text><tr><text>на вершине горы</text></tr></ex></tr><tr pos="существительное"><text>вершина горы</text><syn pos="существительное"><text>горная вершина</text></syn><mean><text>mountain top</text></mean><mean><text>mountain peak</text></mean></tr></def><def pos="adjective" ts="ˈmaʊntɪntɒp"><text>mountaintop</text><tr pos="прилагательное"><text>горный</text><mean><text>mountain</text></mean></tr></def></DicResult>