<?xml version="1.0" encoding="utf-8"?>
<DicResult><head/><def pos="adjective" ts="ˈnesɪsərɪ"><text>necessary</text><tr pos="прилагательное"><text>необходимый</text><syn pos="прилагательное"><text>нужный</text></syn><mean><text>need</text></mean><ex><text>vitally necessary</text><tr><text>жизненно необходимый</text></tr></ex><ex><text>extremely necessary</text><tr><text>крайне нужный</text></tr></ex></tr></def><def pos="noun" ts="ˈnesɪsərɪ"><text>necessary</text><tr pos="существительное"><text>необходимость</text><mean><text>necessity</text></mean><ex><text>whenever necessary</text><tr><text>при необходимости</text></tr></ex></tr></def><def pos="predicative" ts="ˈnesɪsərɪ"><text>necessary</text><tr pos="предикатив"><text>надо</text><mean><text>must</text></mean><ex><text>compulsorily necessary</text><tr><text>обязательно надо</text></tr></ex></tr></def></DicResult>