<?xml version="1.0" encoding="utf-8"?>
<DicResult><head/><def pos="adjective" ts="ˈpærənɔɪd"><text>paranoid</text><tr pos="прилагательное"><text>параноидальный</text><syn pos="прилагательное"><text>параноидный</text></syn><syn pos="прилагательное"><text>паранойяльный</text></syn><mean><text>paranoiac</text></mean><ex><text>paranoid schizophrenic</text><tr><text>параноидальный шизофреник</text></tr></ex><ex><text>paranoid schizophrenia</text><tr><text>параноидная шизофрения</text></tr></ex></tr></def><def pos="noun" ts="ˈpærənɔɪd"><text>paranoid</text><tr pos="существительное"><text>параноик</text><mean><text>paranoiac</text></mean></tr><tr pos="существительное"><text>паранойя</text><mean><text>paranoia</text></mean></tr></def></DicResult>