<?xml version="1.0" encoding="utf-8"?>
<DicResult><head/><def pos="noun" ts="pləˈtuːn"><text>platoon</text><tr pos="существительное"><text>взвод</text><syn pos="существительное"><text>отряд</text></syn><mean><text>squad</text></mean><mean><text>detachment</text></mean><ex><text>infantry platoon</text><tr><text>пехотный взвод</text></tr></ex></tr></def><def pos="adjective" ts="pləˈtuːn"><text>platoon</text><tr pos="прилагательное"><text>взводный</text><mean><text>toon leader</text></mean><ex><text>platoon sergeant</text><tr><text>взводный сержант</text></tr></ex></tr></def></DicResult>