<?xml version="1.0" encoding="utf-8"?>
<DicResult><head/><def pos="adverb" ts="prəˈvɪʒənəlɪ"><text>provisionally</text><tr pos="наречие"><text>временно</text><syn pos="наречие"><text>предварительно</text></syn><syn pos="наречие"><text>условно</text></syn><mean><text>tentatively</text></mean></tr></def><def pos="adjective" ts="prəˈvɪʒənəlɪ"><text>provisionally</text><tr pos="прилагательное"><text>предварительный</text><syn pos="прилагательное"><text>временный</text></syn><mean><text>tentatively</text></mean></tr></def><def pos="noun" ts="prəˈvɪʒənəlɪ"><text>provisionally</text><tr pos="существительное"><text>в предварительном порядке</text></tr><tr pos="существительное"><text>на временной основе</text></tr></def></DicResult>