<?xml version="1.0" encoding="utf-8"?>
<DicResult><head/><def pos="verb" ts="riːɪnˈfɔːs"><text>reinforce</text><tr pos="глагол"><text>укрепить</text><syn pos="глагол"><text>усилить</text></syn><syn pos="глагол"><text>усиливать</text></syn><syn pos="глагол"><text>укреплять</text></syn><syn pos="глагол"><text>упрочить</text></syn><syn pos="глагол"><text>армировать</text></syn><mean><text>strengthen</text></mean><ex><text>with reinforced corners</text><tr><text>с укрепленными углами</text></tr></ex><ex><text>reinforce concrete</text><tr><text>усилить бетон</text></tr></ex><ex><text>mutually reinforce</text><tr><text>взаимно усиливать</text></tr></ex><ex><text>only reinforce</text><tr><text>только укреплять</text></tr></ex><ex><text>reinforced concrete</text><tr><text>армированный бетон</text></tr></ex></tr><tr pos="глагол"><text>подкреплять</text><syn pos="глагол"><text>подкрепить</text></syn><mean><text>underpin</text></mean><ex><text>reinforce each other</text><tr><text>подкреплять друг друга</text></tr></ex></tr><tr pos="глагол"><text>закрепить</text><syn pos="глагол"><text>закреплять</text></syn><mean><text>fasten</text></mean><mean><text>enshrine</text></mean></tr><tr pos="глагол"><text>активизировать</text><mean><text>intensify</text></mean></tr></def><def pos="noun" ts="riːɪnˈfɔːs"><text>reinforce</text><tr pos="существительное"><text>укрепление</text><syn pos="существительное"><text>усиление</text></syn><syn pos="существительное"><text>закрепление</text></syn><mean><text>strengthen</text></mean><mean><text>consolidate</text></mean><ex><text>reinforce the encoding</text><tr><text>усиление кодировки</text></tr></ex></tr><tr pos="существительное"><text>подкрепление</text></tr></def><def pos="adjective" ts="riːɪnˈfɔːs"><text>reinforce</text><tr pos="прилагательное"><text>арматурный</text><ex><text>reinforcing steel</text><tr><text>арматурная сталь</text></tr></ex></tr></def></DicResult>