<?xml version="1.0" encoding="utf-8"?>
<DicResult><head/><def pos="participle" ts="rɪˈnjuːəbl"><text>renewable</text><tr pos="причастие"><text>возобновляемый</text></tr><tr pos="причастие"><text>обновляемый</text><ex><text>daily renewable</text><tr><text>ежедневно обновляемый</text></tr></ex></tr></def><def pos="noun" ts="rɪˈnjuːəbl"><text>renewable</text><tr pos="существительное"><text>ВИЭ</text></tr><tr pos="существительное"><text>возобновляемые виды</text></tr><tr pos="существительное"><text>использование возобновляемых источников</text></tr></def><def pos="adjective" ts="rɪˈnjuːəbl"><text>renewable</text><tr pos="прилагательное"><text>возобновимый</text><ex><text>renewable sources</text><tr><text>возобновимые источники</text></tr></ex></tr><tr pos="прилагательное"><text>восстановимый</text></tr></def></DicResult>