<?xml version="1.0" encoding="utf-8"?>
<DicResult><head/><def pos="noun" ts="rəʊb"><text>robe</text><tr pos="существительное"><text>одежда</text><syn pos="существительное"><text>одеяние</text></syn><syn pos="существительное"><text>платье</text></syn><syn pos="существительное"><text>риза</text></syn><syn pos="существительное"><text>балахон</text></syn><syn pos="существительное"><text>облачение</text></syn><mean><text>clothes</text></mean><mean><text>apparel</text></mean><mean><text>dress</text></mean><mean><text>garment</text></mean><mean><text>vestment</text></mean><ex><text>white robe</text><tr><text>белая одежда</text></tr></ex><ex><text>yellow robe</text><tr><text>желтое одеяние</text></tr></ex><ex><text>black robe</text><tr><text>черное платье</text></tr></ex></tr><tr pos="существительное"><text>халат</text><syn pos="существительное"><text>халатик</text></syn><syn pos="существительное"><text>пеньюар</text></syn><mean><text>gown</text></mean><ex><text>Terry robe</text><tr><text>махровые халаты</text></tr></ex></tr><tr pos="существительное"><text>мантия</text><syn pos="существительное"><text>ряса</text></syn><syn pos="существительное"><text>плащ</text></syn><syn pos="существительное"><text>хитон</text></syn><syn pos="существительное"><text>сутана</text></syn><mean><text>mantle</text></mean><mean><text>cassock</text></mean><mean><text>cloak</text></mean><mean><text>tunic</text></mean><ex><text>brown robe</text><tr><text>коричневая ряса</text></tr></ex></tr><tr pos="существительное"><text>Роба</text><mean><text>uniform</text></mean><ex><text>dress robes</text><tr><text>парадная Роба</text></tr></ex></tr><tr pos="существительное"><text>кимоно</text><mean><text>kimono</text></mean></tr><tr pos="существительное"><text>милоть</text></tr></def></DicResult>