<?xml version="1.0" encoding="utf-8"?>
<DicResult><head/><def pos="noun" ts="sɔːlt"><text>salt</text><tr pos="существительное"><text>соль</text><ex><text>disodium salt</text><tr><text>динатриевая соль</text></tr></ex></tr><tr pos="существительное"><text>солонка</text></tr></def><def pos="adjective" ts="sɔːlt"><text>salt</text><tr pos="прилагательное"><text>соленый</text><syn pos="прилагательное"><text>солевой</text></syn><syn pos="прилагательное"><text>соляной</text></syn><mean><text>saline</text></mean><ex><text>salt cucumber</text><tr><text>соленый огурец</text></tr></ex><ex><text>salt laxative</text><tr><text>солевые слабительные</text></tr></ex><ex><text>salt fog</text><tr><text>соляной туман</text></tr></ex></tr></def><def pos="verb" ts="sɔːlt"><text>salt</text><tr pos="глагол"><text>подсолить</text><ex><text>in salted water</text><tr><text>в подсоленной воде</text></tr></ex></tr></def></DicResult>