<?xml version="1.0" encoding="utf-8"?>
<DicResult><head/><def pos="noun" ts="sɜːf"><text>surf</text><tr pos="существительное"><text>серфинг</text><mean><text>surfing</text></mean></tr><tr pos="существительное"><text>прибой</text><mean><text>tide</text></mean><ex><text>sea surf</text><tr><text>морской прибой</text></tr></ex></tr><tr pos="существительное"><text>поиск</text><ex><text>surf the web</text><tr><text>поиск в интернете</text></tr></ex></tr><tr pos="существительное"><text>серф</text><ex><text>surf music</text><tr><text>серф-музыка</text></tr></ex></tr><tr pos="существительное"><text>по поиску</text><mean><text>on search</text></mean></tr></def><def pos="verb" ts="sɜːf"><text>surf</text><tr pos="глагол"><text>путешествовать</text><mean><text>travel</text></mean><ex><text>surf the Internet</text><tr><text>путешествовать по интернету</text></tr></ex></tr><tr pos="глагол"><text>просматривать</text><mean><text>browse</text></mean></tr><tr pos="глагол"><text>заниматься серфингом</text><syn pos="глагол"><text>серфить</text></syn><mean><text>surfing</text></mean></tr><tr pos="глагол"><text>бродить</text><syn pos="глагол"><text>побродить</text></syn><mean><text>wander</text></mean></tr><tr pos="глагол"><text>выходить</text></tr><tr pos="глагол"><text>бороздить</text></tr></def></DicResult>