<?xml version="1.0" encoding="utf-8"?>
<DicResult><head/><def pos="adjective" ts="ˈswɔmpɪ"><text>swampy</text><tr pos="прилагательное"><text>болотистый</text><syn pos="прилагательное"><text>заболоченный</text></syn><syn pos="прилагательное"><text>болотный</text></syn><mean><text>marshy</text></mean><mean><text>boggy</text></mean><ex><text>swampy terrain</text><tr><text>болотистая местность</text></tr></ex></tr></def><def pos="noun" ts="ˈswɔmpɪ"><text>swampy</text><tr pos="существительное"><text>болото</text></tr></def></DicResult>