<?xml version="1.0" encoding="utf-8"?>
<DicResult><head/><def pos="adjective" ts="ˈtænʤənt"><text>tangent</text><tr pos="прилагательное"><text>касательный</text><ex><text>tangent bifurcation</text><tr><text>касательная бифуркация</text></tr></ex></tr></def><def pos="noun" ts="ˈtænʤənt"><text>tangent</text><tr pos="существительное"><text>тангенс</text><mean><text>dissipation factor</text></mean><ex><text>hyperbolic tangent</text><tr><text>гиперболический тангенс</text></tr></ex></tr><tr pos="существительное"><text>касательная</text></tr></def></DicResult>