<?xml version="1.0" encoding="utf-8"?>
<DicResult><head/><def pos="noun" ts="tempˈteɪʃn"><text>temptation</text><tr pos="существительное"><text>искушение</text><syn pos="существительное"><text>соблазн</text></syn><mean><text>enticement</text></mean><mean><text>stumblingblock</text></mean><ex><text>fall into temptation</text><tr><text>впасть в искушение</text></tr></ex><ex><text>resist the temptation</text><tr><text>устоять перед соблазном</text></tr></ex></tr><tr pos="существительное"><text>заманчивость</text></tr><tr pos="существительное"><text>искус</text></tr></def><def pos="verb" ts="tempˈteɪʃn"><text>temptation</text><tr pos="глагол"><text>соблазниться</text></tr></def></DicResult>