<?xml version="1.0" encoding="utf-8"?>
<DicResult><head/><def pos="adverb" ts="ˈtaɪtlɪ"><text>tightly</text><tr pos="наречие"><text>плотно</text><syn pos="наречие"><text>тесно</text></syn><syn pos="наречие"><text>крепко</text></syn><syn pos="наречие"><text>жестко</text></syn><syn pos="наречие"><text>сильно</text></syn><syn pos="наречие"><text>наглухо</text></syn><syn pos="наречие"><text>герметично</text></syn><syn pos="наречие"><text>прочно</text></syn><syn pos="наречие"><text>намертво</text></syn><syn pos="наречие"><text>накрепко</text></syn><syn pos="наречие"><text>вплотную</text></syn><syn pos="наречие"><text>покрепче</text></syn><syn pos="наречие"><text>неплотно</text></syn><mean><text>densely</text></mean><mean><text>closely</text></mean><mean><text>firmly</text></mean><mean><text>rigidly</text></mean><mean><text>strongly</text></mean><mean><text>hermetically</text></mean><mean><text>tight</text></mean><ex><text>tightly close</text><tr><text>плотно закрыть</text></tr></ex><ex><text>tightly integrate</text><tr><text>тесно интегрировать</text></tr></ex><ex><text>so tightly</text><tr><text>так крепко</text></tr></ex><ex><text>tightly control</text><tr><text>жестко контролировать</text></tr></ex><ex><text>too tightly</text><tr><text>слишком сильно</text></tr></ex><ex><text>tightly closed</text><tr><text>герметично закрытый</text></tr></ex></tr><tr pos="наречие"><text>неразрывно</text><mean><text>inseparably</text></mean></tr></def><def pos="adjective" ts="ˈtaɪtlɪ"><text>tightly</text><tr pos="прилагательное"><text>тугой</text><syn pos="прилагательное"><text>плотный</text></syn><mean><text>tight</text></mean></tr><tr pos="прилагательное"><text>строгий</text><mean><text>strictly</text></mean></tr></def></DicResult>