<?xml version="1.0" encoding="utf-8"?>
<DicResult><head/><def pos="noun" ts="tjuːˈbɜːkjʊlɪn"><text>tuberculin</text><tr pos="существительное"><text>туберкулин</text><ex><text>standard tuberculin</text><tr><text>стандартный туберкулин</text></tr></ex></tr><tr pos="существительное"><text>туберкулиновая проба</text></tr></def><def pos="adjective" ts="tjuːˈbɜːkjʊlɪn"><text>tuberculin</text><tr pos="прилагательное"><text>туберкулиновый</text><ex><text>tuberculin sensitivity</text><tr><text>туберкулиновая чувствительность</text></tr></ex></tr></def></DicResult>