<?xml version="1.0" encoding="utf-8"?>
<DicResult><head/><def pos="adverb" ts="ʌnəkˈseptəblɪ"><text>unacceptably</text><tr pos="наречие"><text>неприемлемо</text><syn pos="наречие"><text>недопустимо</text></syn><syn pos="наречие"><text>непозволительно</text></syn><mean><text>inadmissibly</text></mean><ex><text>unacceptably high</text><tr><text>неприемлемо высокий</text></tr></ex><ex><text>unacceptably low</text><tr><text>недопустимо низкий</text></tr></ex></tr></def><def pos="adjective" ts="ʌnəkˈseptəblɪ"><text>unacceptably</text><tr pos="прилагательное"><text>неприемлемый</text><syn pos="прилагательное"><text>недопустимый</text></syn></tr></def></DicResult>