<?xml version="1.0" encoding="utf-8"?>
<DicResult><head/><def pos="adjective" ts="ˈʌnˈwaɪz"><text>unwise</text><tr pos="прилагательное"><text>неразумный</text><syn pos="прилагательное"><text>неблагоразумный</text></syn><syn pos="прилагательное"><text>немудрый</text></syn><syn pos="прилагательное"><text>глупый</text></syn><mean><text>unreasonable</text></mean><mean><text>imprudent</text></mean><mean><text>stupid</text></mean><ex><text>unwise virgin</text><tr><text>неразумная дева</text></tr></ex></tr><tr pos="прилагательное"><text>неумный</text><mean><text>unintelligent</text></mean></tr></def><def pos="adverb" ts="ˈʌnˈwaɪz"><text>unwise</text><tr pos="наречие"><text>неразумно</text><syn pos="наречие"><text>неблагоразумно</text></syn><mean><text>unreasonable</text></mean><mean><text>imprudent</text></mean></tr><tr pos="наречие"><text>неумно</text></tr></def></DicResult>